hirola/__init__.py
hirola/_hash_table.py
hirola/_version.py
hirola/exceptions.py
hirola/hash_table-Windows-64bit.dll
hirola/hash_table.json
hirola/hook-hirola.py
hirola-0.3.0.dist-info/LICENSE
hirola-0.3.0.dist-info/METADATA
hirola-0.3.0.dist-info/WHEEL
hirola-0.3.0.dist-info/entry_points.txt
hirola-0.3.0.dist-info/top_level.txt
hirola-0.3.0.dist-info/RECORD
