Metadata-Version: 2.1
Name: hirola
Version: 0.3.0
Summary: NumPy vectorized hash table for fast set and dict operations.
Home-page: https://github.com/bwoodsend/hirola
Author: Brénainn Woodsend
Author-email: bwoodsend@gmail.com
License: MIT license
Keywords: NumPy Hash-table dict set
Classifier: Intended Audience :: Developers
Classifier: License :: OSI Approved :: MIT License
Classifier: Natural Language :: English
Classifier: Programming Language :: Python :: 3
Classifier: Programming Language :: Python :: 3.6
Classifier: Programming Language :: Python :: 3.7
Classifier: Programming Language :: Python :: 3.8
Classifier: Programming Language :: Python :: 3.9
Classifier: Programming Language :: Python :: 3.10
Requires-Python: >=3.6
License-File: LICENSE
Requires-Dist: cslug
Requires-Dist: numpy
Provides-Extra: test
Requires-Dist: pytest (>=3) ; extra == 'test'
Requires-Dist: pytest-order ; extra == 'test'
Requires-Dist: coverage ; extra == 'test'
Requires-Dist: pytest-cov ; extra == 'test'
Requires-Dist: coverage-conditional-plugin ; extra == 'test'
